ag/funutils/__init__.py
ag/funutils/fun.py
ag/funutils/maybe.py
ag.funutils-1.2.dist-info/LICENSE
ag.funutils-1.2.dist-info/METADATA
ag.funutils-1.2.dist-info/WHEEL
ag.funutils-1.2.dist-info/top_level.txt
ag.funutils-1.2.dist-info/RECORD
