Metadata-Version: 2.1
Name: ag.funutils
Version: 1.2
Summary: Fun functional utilities
Home-page: https://github.com/austin-garrard/ag.funutils
Author: Austin Garrard
Author-email: austin.w.garrard@gmail.com
License: UNKNOWN
Platform: UNKNOWN
